CHANGELOG.txt
LICENSE.txt
MANIFEST.in
README.md
README.txt
setup.py
.eggs/README.txt
.eggs/atomicwrites-1.4.0-py3.8.egg/EGG-INFO/top_level.txt
.eggs/atomicwrites-1.4.0-py3.8.egg/atomicwrites/__init__.py
.eggs/attrs-20.3.0-py3.8.egg/EGG-INFO/requires.txt
.eggs/attrs-20.3.0-py3.8.egg/EGG-INFO/top_level.txt
.eggs/attrs-20.3.0-py3.8.egg/attr/__init__.py
.eggs/attrs-20.3.0-py3.8.egg/attr/_compat.py
.eggs/attrs-20.3.0-py3.8.egg/attr/_config.py
.eggs/attrs-20.3.0-py3.8.egg/attr/_funcs.py
.eggs/attrs-20.3.0-py3.8.egg/attr/_make.py
.eggs/attrs-20.3.0-py3.8.egg/attr/_next_gen.py
.eggs/attrs-20.3.0-py3.8.egg/attr/_version_info.py
.eggs/attrs-20.3.0-py3.8.egg/attr/converters.py
.eggs/attrs-20.3.0-py3.8.egg/attr/exceptions.py
.eggs/attrs-20.3.0-py3.8.egg/attr/filters.py
.eggs/attrs-20.3.0-py3.8.egg/attr/setters.py
.eggs/attrs-20.3.0-py3.8.egg/attr/validators.py
.eggs/more_itertools-8.7.0-py3.8.egg/EGG-INFO/top_level.txt
.eggs/more_itertools-8.7.0-py3.8.egg/more_itertools/__init__.py
.eggs/more_itertools-8.7.0-py3.8.egg/more_itertools/more.py
.eggs/more_itertools-8.7.0-py3.8.egg/more_itertools/recipes.py
.eggs/pluggy-1.0.0.dev0-py3.8.egg/EGG-INFO/requires.txt
.eggs/pluggy-1.0.0.dev0-py3.8.egg/EGG-INFO/top_level.txt
.eggs/pluggy-1.0.0.dev0-py3.8.egg/pluggy/__init__.py
.eggs/pluggy-1.0.0.dev0-py3.8.egg/pluggy/_tracing.py
.eggs/pluggy-1.0.0.dev0-py3.8.egg/pluggy/_version.py
.eggs/pluggy-1.0.0.dev0-py3.8.egg/pluggy/callers.py
.eggs/pluggy-1.0.0.dev0-py3.8.egg/pluggy/hooks.py
.eggs/pluggy-1.0.0.dev0-py3.8.egg/pluggy/manager.py
.eggs/py-1.10.0-py3.8.egg/EGG-INFO/top_level.txt
.eggs/py-1.10.0-py3.8.egg/py/__init__.py
.eggs/py-1.10.0-py3.8.egg/py/__metainfo.py
.eggs/py-1.10.0-py3.8.egg/py/_builtin.py
.eggs/py-1.10.0-py3.8.egg/py/_error.py
.eggs/py-1.10.0-py3.8.egg/py/_std.py
.eggs/py-1.10.0-py3.8.egg/py/_version.py
.eggs/py-1.10.0-py3.8.egg/py/_xmlgen.py
.eggs/py-1.10.0-py3.8.egg/py/test.py
.eggs/py-1.10.0-py3.8.egg/py/_code/__init__.py
.eggs/py-1.10.0-py3.8.egg/py/_code/_assertionnew.py
.eggs/py-1.10.0-py3.8.egg/py/_code/_assertionold.py
.eggs/py-1.10.0-py3.8.egg/py/_code/_py2traceback.py
.eggs/py-1.10.0-py3.8.egg/py/_code/assertion.py
.eggs/py-1.10.0-py3.8.egg/py/_code/code.py
.eggs/py-1.10.0-py3.8.egg/py/_code/source.py
.eggs/py-1.10.0-py3.8.egg/py/_io/__init__.py
.eggs/py-1.10.0-py3.8.egg/py/_io/capture.py
.eggs/py-1.10.0-py3.8.egg/py/_io/saferepr.py
.eggs/py-1.10.0-py3.8.egg/py/_vendored_packages/apipkg-1.5.dist-info/top_level.txt
.eggs/py-1.10.0-py3.8.egg/py/_vendored_packages/iniconfig-1.1.1.dist-info/top_level.txt
.eggs/pytest-4.4.1-py3.8.egg/EGG-INFO/entry_points.txt
.eggs/pytest-4.4.1-py3.8.egg/EGG-INFO/requires.txt
.eggs/pytest-4.4.1-py3.8.egg/EGG-INFO/top_level.txt
.eggs/pytest_runner-5.2-py3.8.egg/EGG-INFO/entry_points.txt
.eggs/pytest_runner-5.2-py3.8.egg/EGG-INFO/requires.txt
.eggs/pytest_runner-5.2-py3.8.egg/EGG-INFO/top_level.txt
deepNets.egg-info/PKG-INFO
deepNets.egg-info/SOURCES.txt
deepNets.egg-info/dependency_links.txt
deepNets.egg-info/requires.txt
deepNets.egg-info/top_level.txt
env/lib/python3.8/site-packages/atomicwrites-1.4.0.dist-info/top_level.txt
env/lib/python3.8/site-packages/attrs-20.3.0.dist-info/top_level.txt
env/lib/python3.8/site-packages/more_itertools-8.6.0.dist-info/top_level.txt
env/lib/python3.8/site-packages/numpy-1.19.4.dist-info/LICENSE.txt
env/lib/python3.8/site-packages/numpy-1.19.4.dist-info/LICENSES_bundled.txt
env/lib/python3.8/site-packages/numpy-1.19.4.dist-info/entry_points.txt
env/lib/python3.8/site-packages/numpy-1.19.4.dist-info/top_level.txt
env/lib/python3.8/site-packages/pip-20.3.3.dist-info/LICENSE.txt
env/lib/python3.8/site-packages/pip-20.3.3.dist-info/entry_points.txt
env/lib/python3.8/site-packages/pip-20.3.3.dist-info/top_level.txt
env/lib/python3.8/site-packages/pluggy-0.13.1.dist-info/top_level.txt
env/lib/python3.8/site-packages/py-1.10.0.dist-info/top_level.txt
env/lib/python3.8/site-packages/py/_vendored_packages/apipkg-1.5.dist-info/top_level.txt
env/lib/python3.8/site-packages/py/_vendored_packages/iniconfig-1.1.1.dist-info/top_level.txt
env/lib/python3.8/site-packages/pytest-4.4.1.dist-info/entry_points.txt
env/lib/python3.8/site-packages/pytest-4.4.1.dist-info/top_level.txt
env/lib/python3.8/site-packages/pytest_runner-4.4.dist-info/entry_points.txt
env/lib/python3.8/site-packages/pytest_runner-4.4.dist-info/namespace_packages.txt
env/lib/python3.8/site-packages/pytest_runner-4.4.dist-info/top_level.txt
env/lib/python3.8/site-packages/setuptools-50.3.2.dist-info/dependency_links.txt
env/lib/python3.8/site-packages/setuptools-50.3.2.dist-info/entry_points.txt
env/lib/python3.8/site-packages/setuptools-50.3.2.dist-info/top_level.txt
env/lib/python3.8/site-packages/six-1.15.0.dist-info/top_level.txt
env/lib/python3.8/site-packages/wheel-0.35.1.dist-info/LICENSE.txt
env/lib/python3.8/site-packages/wheel-0.35.1.dist-info/entry_points.txt
env/lib/python3.8/site-packages/wheel-0.35.1.dist-info/top_level.txt
