Metadata-Version: 1.1
Name: deepNets
Version: 0.1.7
Summary: A basic deep learning tool
Home-page: UNKNOWN
Author: Deepak Velmurugan
Author-email: deepazlions@gmail.com
License: MIT
Keywords: deepLearning
Platform: UNKNOWN
Classifier: Development Status :: 5 - Production/Stable
Classifier: Intended Audience :: Education
Classifier: Operating System :: MacOS
Classifier: Operating System :: Microsoft :: Windows
Classifier: Operating System :: POSIX :: Linux
Classifier: License :: OSI Approved :: MIT License
Classifier: Programming Language :: Python :: 3.7
Classifier: Programming Language :: Python :: 3.8
